{
  "id": "bossa-syncopation",
  "name": "Bossa (مƒ«مƒ¼مƒˆمƒ¬م‚¹ه’Œéں³+2ه°ڈç¯€م‚·مƒ³م‚³مƒڑمƒ¼م‚·مƒ§مƒ³)",
  "stylePrompt": "intimate bossa nova, straight-eighth nylon-string guitar with a two-bar syncopated comping pattern, subtle rootless piano fills, root-and-fifth acoustic bass with anticipations, brushed cross-stick percussion, extended jazz harmony, airy conversational vocal",
  "defaults": {
    "key": "F",
    "mode": "major",
    "bpm": 124,
    "meter": "4/4",
    "arrangement": {
      "pianoPattern": "bossa",
      "guitarPattern": "bossa",
      "drumPattern": "bossa",
      "swing": 0.02,
      "humanize": 0.08,
      "velocityScale": 0.86
    }
  },
  "chord": {
    "vocabulary": ["Iâ–³9", "I7", "ii9", "II7", "III7", "iii7", "IVâ–³9", "iv7", "V9", "VI7", "vi9", "viiأ¸7"],
    "transitions": {
      "Iâ–³9": { "VI7": 0.22, "vi9": 0.2, "IVâ–³9": 0.18, "iii7": 0.15, "I7": 0.15, "III7": 0.1 },
      "I7": { "IVâ–³9": 0.7, "iv7": 0.3 },
      "ii9": { "V9": 0.78, "VI7": 0.12, "IVâ–³9": 0.1 },
      "II7": { "V9": 0.75, "ii9": 0.25 },
      "III7": { "vi9": 0.72, "VI7": 0.18, "IVâ–³9": 0.1 },
      "iii7": { "VI7": 0.55, "vi9": 0.3, "ii9": 0.15 },
      "IVâ–³9": { "iv7": 0.25, "iii7": 0.2, "Iâ–³9": 0.2, "ii9": 0.2, "V9": 0.15 },
      "iv7": { "Iâ–³9": 0.55, "V9": 0.45 },
      "V9": { "Iâ–³9": 0.65, "vi9": 0.2, "III7": 0.15 },
      "VI7": { "ii9": 0.75, "IVâ–³9": 0.15, "V9": 0.1 },
      "vi9": { "ii9": 0.35, "II7": 0.3, "IVâ–³9": 0.2, "III7": 0.15 },
      "viiأ¸7": { "Iâ–³9": 0.5, "III7": 0.3, "V9": 0.2 }
    },
    "idioms": [
      { "symbols": ["Iâ–³9", "VI7", "ii9", "V9"], "weight": 4 },
      { "symbols": ["iii7", "VI7", "ii9", "V9"], "weight": 3 },
      { "symbols": ["Iâ–³9", "I7", "IVâ–³9", "iv7"], "weight": 3 },
      { "symbols": ["vi9", "II7", "V9", "Iâ–³9"], "weight": 2 },
      { "symbols": ["ii9", "V9", "Iâ–³9"], "weight": 3 }
    ],
    "idiomProbability": 0.72,
    "cadences": {
      "final": [
        { "symbols": ["V9", "Iâ–³9"], "weight": 4 },
        { "symbols": ["iv7", "Iâ–³9"], "weight": 2 },
        { "symbols": ["IVâ–³9", "Iâ–³9"], "weight": 1 }
      ],
      "half": [
        { "symbols": ["ii9"], "weight": 3 },
        { "symbols": ["V9"], "weight": 2 },
        { "symbols": ["VI7"], "weight": 1 }
      ]
    },
    "harmonicRhythm": {
      "default": { "1": 0.3, "2": 0.7 },
      "intro": { "0.5": 0.15, "1": 0.65, "2": 0.2 },
      "chorus": { "1": 0.2, "2": 0.8 }
    },
    "cliches": [],
    "borrowedChords": true
  },
  "rhythm": {
    "templates": {
      "4/4": [
        { "beats": [-0.5, 0.5, 1, 0.5, 0.5, 1], "weight": 4 },
        { "beats": [1, -0.5, 0.5, 1.5, 0.5], "weight": 3 },
        { "beats": [0.5, 0.5, -0.5, 0.5, 1, 1], "weight": 3 },
        { "beats": [-1, 0.5, 0.5, 1.5, 0.5], "weight": 2 },
        { "beats": [1.5, 0.5, -0.5, 0.5, 1], "weight": 2 }
      ]
    },
    "finalTemplates": {
      "4/4": [
        { "beats": [-0.5, 0.5, 1, 2], "weight": 3 },
        { "beats": [1, -0.5, 0.5, 2], "weight": 2 },
        { "beats": [2, 2], "weight": 1 }
      ]
    },
    "anacrusisProbability": 0.42,
    "chorusDensityBias": 0.06
  },
  "melody": {
    "leapProbability": { "default": 0.07, "chorusHead": 0.16 },
    "leapRangeSemitones": [4, 7],
    "afterLeapBias": "down",
    "contour": "syncopated-narrow",
    "pedalPoint": false,
    "repeatNoteProbability": 0.18,
    "motif": { "repeatProbability": 0.72 },
    "nonChordTones": { "appoggiatura": 0.06, "suspension": 0.12, "chromaticPassing": 0.1 },
    "registerShift": { "chorus": 1 }
  },
  "structure": {
    "phraseLengths": [4, 4],
    "irregularPhraseProbability": 0
  },
  "groove": {
    "subdivision": 0.5,
    "accentPattern": [0.5, 1.5, 3],
    "anticipation": 0.5,
    "bassPattern": "bossa"
  },
  "sectionRules": {
    "intro": { "phraseLengths": [4], "idiomProbability": 0.5 },
    "verse": { "idiomProbability": 0.72 },
    "chorus": { "idiomProbability": 0.82 },
    "outro": { "phraseLengths": [4] }
  },
  "modulation": {
    "bridge": {
      "probability": 0.22,
      "intervals": [
        { "semitones": -2, "weight": 1 },
        { "semitones": 5, "weight": 1 }
      ]
    }
  }
}
